aresilient/__init__.py
aresilient/callbacks.py
aresilient/config.py
aresilient/delete.py
aresilient/delete_async.py
aresilient/exceptions.py
aresilient/get.py
aresilient/get_async.py
aresilient/head.py
aresilient/head_async.py
aresilient/options.py
aresilient/options_async.py
aresilient/patch.py
aresilient/patch_async.py
aresilient/post.py
aresilient/post_async.py
aresilient/put.py
aresilient/put_async.py
aresilient/py.typed
aresilient/request.py
aresilient/request_async.py
aresilient/utils.py
aresilient-0.0.1a0.dist-info/METADATA
aresilient-0.0.1a0.dist-info/WHEEL
aresilient-0.0.1a0.dist-info/licenses/LICENSE
aresilient-0.0.1a0.dist-info/RECORD
