Metadata-Version: 2.4
Name: aresilient
Version: 0.0.1a0
Dynamic: Maintainer
Dynamic: Maintainer-email
Summary: Python library focused on common HTTP request functionality
Project-URL: Homepage, https://github.com/durandtibo/aresilient
Project-URL: Repository, https://github.com/durandtibo/aresilient
Project-URL: Documentation, https://durandtibo.github.io/aresilient/
Project-URL: Changelog, https://github.com/durandtibo/aresilient/releases
Project-URL: Issues, https://github.com/durandtibo/aresilient/issues
Author-email: Thibaut Durand <durand.tibo+gh@gmail.com>
License-Expression: BSD-3-Clause
License-File: LICENSE
Keywords: api,client,http,httpx,networking,requests,resilience,retry
Classifier: Development Status :: 3 - Alpha
Classifier: Intended Audience :: Developers
Classifier: Intended Audience :: Science/Research
Classifier: License :: OSI Approved :: BSD License
Classifier: Operating System :: MacOS
Classifier: Operating System :: POSIX :: Linux
Classifier: Programming Language :: Python :: 3.10
Classifier: Programming Language :: Python :: 3.11
Classifier: Programming Language :: Python :: 3.12
Classifier: Programming Language :: Python :: 3.13
Classifier: Programming Language :: Python :: 3.14
Classifier: Topic :: Scientific/Engineering
Classifier: Topic :: Software Development :: Libraries
Requires-Python: >=3.10
Requires-Dist: httpx<1.0,>=0.28
Provides-Extra: all
